[{"model": "appdogustavo.motivos", "pk": 1, "fields": {"title": "Ele tem um sorriso muito carismático", "relevancia": "É importante um pokemon ser amigável e acolhedor", "ExpressividadeInGame": "M", "categoria": "B"}}, {"model": "appdogustavo.motivos", "pk": 2, "fields": {"title": "A versão shiny dele é muito bonita", "relevancia": "Caçar shinies é um dos melhores passa-tempos após completar o jogo", "ExpressividadeInGame": "P", "categoria": "B"}}, {"model": "appdogustavo.motivos", "pk": 3, "fields": {"title": "A última evolução dele tem uma combinação boa de elementos", "relevancia": "No competitivo, os tipos são uma das coisas mais importantes", "ExpressividadeInGame": "G", "categoria": "C"}}, {"model": "appdogustavo.motivos", "pk": 4, "fields": {"title": "A mega evolução dele é bombada", "relevancia": "Ter uma aparência engraçada pode ser definitivo para ser escolhido", "ExpressividadeInGame": "M", "categoria": "E"}}, {"model": "appdogustavo.pokemons", "pk": 1, "fields": {"title": "Spheal", "tipo": "Ice/Water", "tamanho": "0,8 m", "peso": "39,5 kg", "img": "https://assets.pokemon.com/assets/cms2/img/pokedex/full/363.png", "color": "#6487c2"}}, {"model": "appdogustavo.pokemons", "pk": 2, "fields": {"title": "Decidueye", "tipo": "Grass/Fighting", "tamanho": "1,6 m", "peso": "37,0 kg", "img": "https://legends.pokemon.com/assets/pokemon/pokemon_decidueye.png", "color": "#bc1a23"}}, {"model": "appdogustavo.pokemons", "pk": 3, "fields": {"title": "Ampharos", "tipo": "Electric", "tamanho": "1,4 m", "peso": "61,5 kg", "img": "https://static.pokemonpets.com/images/monsters-images-800-800/181-Ampharos.webp", "color": "#ec910b"}}, {"model": "appdogustavo.pokemons", "pk": 4, "fields": {"title": "Abomasnow", "tipo": "Grass/Ice", "tamanho": "2,2 m", "peso": "135,5 kg", "img": "https://images.gameinfo.io/pokemon/256/p460f375.png", "color": "#497572"}}, {"model": "appdogustavo.tabeladata", "pk": 1, "fields": {"title": "HP", "statS": 100, "statM": 100}}, {"model": "appdogustavo.tabeladata", "pk": 2, "fields": {"title": "Attack", "statS": 110, "statM": 150}}, {"model": "appdogustavo.tabeladata", "pk": 3, "fields": {"title": "Defense", "statS": 90, "statM": 110}}, {"model": "appdogustavo.tabeladata", "pk": 4, "fields": {"title": "Sp. Atk.", "statS": 85, "statM": 95}}, {"model": "appdogustavo.tabeladata", "pk": 5, "fields": {"title": "Sp. Def.", "statS": 90, "statM": 110}}, {"model": "appdogustavo.tabeladata", "pk": 6, "fields": {"title": "Speed", "statS": 60, "statM": 70}}, {"model": "appdogustavo.tabeladata", "pk": 7, "fields": {"title": "Total", "statS": 535, "statM": 635}}]